homm3data/__init__.py
homm3data/deffile.py
homm3data/lodfile.py
homm3data/pakfile.py
homm3data/pcxfile.py
homm3data-0.1.10.dist-info/licenses/LICENSE
homm3data-0.1.10.dist-info/METADATA
homm3data-0.1.10.dist-info/WHEEL
homm3data-0.1.10.dist-info/top_level.txt
homm3data-0.1.10.dist-info/RECORD
