Metadata-Version: 2.4
Name: homm3data
Version: 0.1.10
Summary: Decoding of Heroes Might of Magic III files
Home-page: https://github.com/Laserlicht/homm3data
Author: Laserlicht
License: MIT
Keywords: homm3 heroes iii might magic def lod pak
License-File: LICENSE
Requires-Dist: pillow>=10.3.0
Requires-Dist: numpy>=1.26.4
Dynamic: author
Dynamic: description
Dynamic: description-content-type
Dynamic: home-page
Dynamic: keywords
Dynamic: license
Dynamic: license-file
Dynamic: requires-dist
Dynamic: summary
